[
  {
    "title": "Chicken & Rice Bowl",
    "ingredients": ["chicken", "rice", "soy sauce", "oil", "salt"],
    "time": "25 minutes",
    "diets": ["halal", "kosher"],
    "steps": [
      "Cook rice according to package instructions.",
      "Season and pan-fry chicken until cooked through.",
      "Mix chicken with soy sauce and serve over rice with steamed veggies."
    ],
    "tags": ["chicken", "rice", "easy"]
  },
  {
    "title": "Chicken Stir-Fry",
    "ingredients": ["chicken", "broccoli", "soy sauce", "garlic", "oil"],
    "time": "20 minutes",
    "diets": ["halal", "kosher"],
    "steps": [
      "Cut chicken into cubes and season lightly.",
      "Stir-fry garlic and chicken in hot oil until golden.",
      "Add broccoli and soy sauce, cook until tender-crisp."
    ],
    "tags": ["chicken", "stir-fry", "quick"]
  },
  {
    "title": "One-Pan Chicken & Veggies",
    "ingredients": ["chicken", "potato", "carrot", "oil", "salt"],
    "time": "35 minutes",
    "diets": ["halal", "kosher"],
    "steps": [
      "Toss chopped chicken and veggies with oil and seasoning.",
      "Roast on a sheet pan at 200°C until cooked through.",
      "Serve hot."
    ],
    "tags": ["chicken", "roast"]
  },
  {
    "title": "Tomato Pasta",
    "ingredients": ["pasta", "tomato", "garlic", "olive oil", "salt"],
    "time": "20 minutes",
    "diets": ["vegetarian", "vegan"],
    "steps": [
      "Cook pasta until al dente.",
      "Sauté garlic in olive oil, add chopped tomatoes and simmer.",
      "Toss pasta with sauce and serve."
    ],
    "tags": ["pasta", "vegetarian"]
  },
  {
    "title": "Fried Rice",
    "ingredients": ["rice", "egg", "carrot", "peas", "soy sauce", "oil"],
    "time": "15 minutes",
    "diets": ["vegetarian"],
    "steps": [
      "Use cold cooked rice for best texture.",
      "Scramble eggs in the pan, set aside.",
      "Stir-fry veggies, add rice and soy sauce, fold eggs back in."
    ],
    "tags": ["rice", "quick"]
  },
  {
    "title": "Veggie Omelette",
    "ingredients": ["egg", "milk", "onion", "bell pepper", "salt", "oil"],
    "time": "10 minutes",
    "diets": ["vegetarian", "kosher"],
    "steps": [
      "Beat eggs with a splash of milk.",
      "Sauté veggies until soft, add egg mixture and cook until set.",
      "Fold and serve."
    ],
    "tags": ["egg", "breakfast"]
  },
  {
    "title": "Grilled Cheese",
    "ingredients": ["bread", "cheese", "butter"],
    "time": "10 minutes",
    "diets": ["vegetarian"],
    "steps": [
      "Butter the bread slices, place cheese between them.",
      "Grill on a pan until golden and cheese melts.",
      "Serve immediately."
    ],
    "tags": ["snack"]
  },
  {
    "title": "Tuna Salad",
    "ingredients": ["tuna", "mayonnaise", "celery", "lettuce"],
    "time": "10 minutes",
    "diets": ["pescatarian", "halal", "kosher"],
    "steps": [
      "Mix drained tuna with mayo and chopped celery.",
      "Serve over lettuce or with bread."
    ],
    "tags": ["salad", "quick"]
  },
  {
    "title": "Pancakes",
    "ingredients": ["flour", "milk", "egg", "butter"],
    "time": "20 minutes",
    "diets": ["vegetarian"],
    "steps": [
      "Mix flour, milk, and egg to a batter.",
      "Fry small pancakes in butter until golden on both sides.",
      "Serve with syrup or fruit."
    ],
    "tags": ["breakfast", "sweet"]
  },
  {
    "title": "Quick Veggie Stir-Fry",
    "ingredients": ["broccoli", "carrot", "soy sauce", "garlic", "oil"],
    "time": "15 minutes",
    "diets": ["vegan", "vegetarian", "halal", "kosher"],
    "steps": [
      "Heat oil and sauté garlic.",
      "Add veggies and stir-fry until tender-crisp.",
      "Finish with soy sauce and serve with rice or noodles."
    ],
    "tags": ["veggie", "quick"]
  },
  {
    "title": "Tofu Stir-Fry",
    "ingredients": ["tofu", "broccoli", "bell pepper", "soy sauce", "garlic", "oil"],
    "time": "20 minutes",
    "diets": ["vegan", "vegetarian"],
    "steps": [
      "Press tofu and cut into cubes.",
      "Pan-fry tofu until golden, set aside.",
      "Stir-fry veggies and garlic, add tofu back with soy sauce, cook until done."
    ],
    "tags": ["tofu", "quick"]
  },
  {
    "title": "Lentil & Vegetable Curry",
    "ingredients": ["lentils", "coconut milk", "tomato", "onion", "garlic", "oil", "curry powder"],
    "time": "30 minutes",
    "diets": ["vegan", "vegetarian"],
    "steps": [
      "Sauté onion and garlic in oil.",
      "Add curry powder, lentils, and coconut milk.",
      "Add tomato and simmer until lentils are tender.",
      "Serve with rice or bread."
    ],
    "tags": ["curry", "vegan"]
  },
  {
    "title": "Grilled Fish with Lemon",
    "ingredients": ["fish", "lemon", "olive oil", "salt", "pepper"],
    "time": "20 minutes",
    "diets": ["pescatarian", "halal", "kosher"],
    "steps": [
      "Brush fish with olive oil and season with salt and pepper.",
      "Grill or pan-fry fish until cooked through (about 5-7 min per side).",
      "Squeeze fresh lemon juice and serve."
    ],
    "tags": ["fish", "pescatarian"]
  }
]
